DOMEventListener-1.9.6.dist-info/DESCRIPTION.rst
DOMEventListener-1.9.6.dist-info/METADATA
DOMEventListener-1.9.6.dist-info/RECORD
DOMEventListener-1.9.6.dist-info/WHEEL
DOMEventListener-1.9.6.dist-info/entry_points.txt
DOMEventListener-1.9.6.dist-info/metadata.json
DOMEventListener-1.9.6.dist-info/top_level.txt
domeventlistener/__init__.py
domeventlistener/bin.py
domeventlistener/listen.py
domeventlistener/pool.py
domeventlistener/utils.py
