Metadata-Version: 2.0
Name: DOMEventListener
Version: 1.9.6
Summary: Subscripe on DOM elements, trigger methods when they change
Home-page: https://github.com/sebbekarlsson/DOMEventListener
Author: UNKNOWN
Author-email: UNKNOWN
License: UNKNOWN
Platform: UNKNOWN
Requires-Dist: requests
Requires-Dist: bs4
